{
    "PlayerBehaviour": {
        "checkpoints": [
            {
                "steps": 17730,
                "file_path": "results/state-rotation/PlayerBehaviour/PlayerBehaviour-17730.onnx",
                "reward": 9.272727272727273,
                "creation_time": 1684907861.946574,
                "auxillary_file_paths": [
                    "results/state-rotation/PlayerBehaviour/PlayerBehaviour-17730.pt"
                ]
            }
        ],
        "final_checkpoint": {
            "steps": 17730,
            "file_path": "results/state-rotation/PlayerBehaviour.onnx",
            "reward": 9.272727272727273,
            "creation_time": 1684907861.946574,
            "auxillary_file_paths": [
                "results/state-rotation/PlayerBehaviour/PlayerBehaviour-17730.pt"
            ]
        }
    },
    "metadata": {
        "stats_format_version": "0.3.0",
        "mlagents_version": "0.30.0",
        "torch_version": "2.1.0.dev20230514"
    }
}